setup.py
nonebot_plugin_CyberSensoji/__init__.py
nonebot_plugin_CyberSensoji/message.py
nonebot_plugin_CyberSensoji.egg-info/PKG-INFO
nonebot_plugin_CyberSensoji.egg-info/SOURCES.txt
nonebot_plugin_CyberSensoji.egg-info/dependency_links.txt
nonebot_plugin_CyberSensoji.egg-info/requires.txt
nonebot_plugin_CyberSensoji.egg-info/top_level.txt