Metadata-Version: 2.1
Name: nonebot-plugin-CyberSensoji
Version: 0.0.2
Summary: A plugin for nonebot
Home-page: https://github.com/Raidenneox/nonebot_plugin_CyberSensoji
Author: Raidenneox
Author-email: longahead@outlook.com
License: MIT Licence
Keywords: pip,CyberSensoji
Platform: any
